one_prompt_agents/__init__.py
one_prompt_agents/agents_loader.py
one_prompt_agents/api.py
one_prompt_agents/chat_utils.py
one_prompt_agents/cli.py
one_prompt_agents/core_chat.py
one_prompt_agents/http_start.py
one_prompt_agents/job_manager.py
one_prompt_agents/logging_setup.py
one_prompt_agents/main.py
one_prompt_agents/mcp_agent.py
one_prompt_agents/mcp_servers_loader.py
one_prompt_agents/mcp_setup.py
one_prompt_agents/strategies.py
one_prompt_agents/utils.py
one_prompt_agents-0.0.3.dist-info/licenses/LICENSE
one_prompt_agents-0.0.3.dist-info/METADATA
one_prompt_agents-0.0.3.dist-info/WHEEL
one_prompt_agents-0.0.3.dist-info/entry_points.txt
one_prompt_agents-0.0.3.dist-info/top_level.txt
one_prompt_agents-0.0.3.dist-info/RECORD
