Metadata-Version: 2.4
Name: one-prompt-agents
Version: 0.0.3
Summary: A small Framework built on top of openai agents sdk to develop one prompt autonomous agents
Author-email: Ivan Postolski <ivan.postolski@gmail.com>
License-File: LICENSE
Requires-Dist: uvicorn==0.34.2
Requires-Dist: pydantic==2.11.4
Requires-Dist: fastmcp==2.3.4
Requires-Dist: openai-agents==0.0.14
Requires-Dist: fastapi==0.115.12
Requires-Dist: requests
Dynamic: license-file
